data_expectations/__init__.py
data_expectations/version.py
data_expectations/errors/__init__.py
data_expectations/errors/base_exception.py
data_expectations/errors/expectation_not_met_error.py
data_expectations/errors/expectation_not_understood_error.py
data_expectations/internals/__init__.py
data_expectations/internals/evaluate.py
data_expectations/internals/expectations.py
data_expectations/internals/text.py
data_expectations/measures/__init__.py
data_expectations/measures/collector.py
data_expectations/measures/measures.py
dataexpectations-0.0.6.dist-info/LICENSE
dataexpectations-0.0.6.dist-info/METADATA
dataexpectations-0.0.6.dist-info/WHEEL
dataexpectations-0.0.6.dist-info/top_level.txt
dataexpectations-0.0.6.dist-info/RECORD
