Metadata-Version: 2.1
Name: dataexpectations
Version: 0.0.6
Summary: Is your data meeting all your expecations
Home-page: https://github.com/joocer/data_expectations
Maintainer: Joocer
License: UNKNOWN
Platform: UNKNOWN
License-File: LICENSE
